mcp_server_weibo/README.md
mcp_server_weibo/__init__.py
mcp_server_weibo/__main__.py
mcp_server_weibo/consts.py
mcp_server_weibo/schemas.py
mcp_server_weibo/server.py
mcp_server_weibo/weibo.py
iflow_mcp_qinyuanpei_mcp_server_weibo-1.0.7.dist-info/METADATA
iflow_mcp_qinyuanpei_mcp_server_weibo-1.0.7.dist-info/WHEEL
iflow_mcp_qinyuanpei_mcp_server_weibo-1.0.7.dist-info/entry_points.txt
iflow_mcp_qinyuanpei_mcp_server_weibo-1.0.7.dist-info/licenses/LICENSE
iflow_mcp_qinyuanpei_mcp_server_weibo-1.0.7.dist-info/RECORD
