Metadata-Version: 2.4
Name: iflow-mcp_qinyuanpei_mcp-server-weibo
Version: 1.0.7
Summary: A MCP Server for Weibo
Project-URL: Repository, https://github.com/qinyuanpei/mcp-server-weibo.git
Project-URL: Issues, https://github.com/qinyuanpei/mcp-server-weibo/issues
License: MIT License
License-File: LICENSE
Keywords: MCP,Model Context Protocol,Python,Social Networks,Weibo
Requires-Python: >=3.10
Requires-Dist: fastmcp
Requires-Dist: httpx
Requires-Dist: mcp[cli]
